cnki_html2json/__init__.py
cnki_html2json/cli.py
cnki_html2json/crawl.py
cnki_html2json/html2json.py
cnki_html2json/parse_metadata.py
cnki_html2json/recognize_slider_coordinate.py
cnki_html2json-0.1.10.dist-info/LICENSE
cnki_html2json-0.1.10.dist-info/METADATA
cnki_html2json-0.1.10.dist-info/WHEEL
cnki_html2json-0.1.10.dist-info/entry_points.txt
cnki_html2json-0.1.10.dist-info/top_level.txt
cnki_html2json-0.1.10.dist-info/RECORD
