Metadata-Version: 2.1
Name: cnki-html2json
Version: 0.1.10
Summary: A package for converting cnki journal papers' html to json
Author-email: WangK2 <kw221225@gmail.com>
License: MIT
Keywords: cnki,text structure,crawler
Classifier: Development Status :: 5 - Production/Stable
Classifier: Intended Audience :: Science/Research
Classifier: License :: OSI Approved :: MIT License
Classifier: Programming Language :: Python :: 3.8
Classifier: Programming Language :: Python :: 3.9
Classifier: Programming Language :: Python :: 3.10
Classifier: Programming Language :: Python :: 3.11
Classifier: Operating System :: OS Independent
Requires-Python: >=3.8
License-File: LICENSE
Requires-Dist: selenium
Requires-Dist: lxml
Requires-Dist: opencv-python
Requires-Dist: numpy
Requires-Dist: loguru
